hairball/__init__.py
hairball/plugins/checks.py
hairball/plugins/duplicate.py
hairball/plugins/__init__.py
hairball/plugins/blocks.py
hairball/plugins/initialization.py
hairball/plugins/convention.py
hairball-0.3.dist-info/DESCRIPTION.rst
hairball-0.3.dist-info/metadata.json
hairball-0.3.dist-info/METADATA
hairball-0.3.dist-info/entry_points.txt
hairball-0.3.dist-info/WHEEL
hairball-0.3.dist-info/top_level.txt
hairball-0.3.dist-info/RECORD
