Metadata-Version: 2.0
Name: hairball
Version: 0.3
Summary: Hairball is a plugin-able framework useful for static analysis of Scratch projects.
Home-page: https://github.com/ucsb-cs-education/hairball
Author: Bryce Boe
Author-email: bbzbryce@gmail.com
License: Simplified BSD License
Keywords: scratch static-analysis
Platform: UNKNOWN
Classifier: Environment :: Console
Classifier: Intended Audience :: Developers
Classifier: License :: OSI Approved :: BSD License
Classifier: Natural Language :: English
Classifier: Operating System :: OS Independent
Classifier: Programming Language :: Python :: 2.7
Classifier: Topic :: Utilities
Requires-Dist: appdirs (>=1.2.0)
Requires-Dist: kurt (>=2.0.5)
